common/__init__.py
common/core/__init__.py
common/core/security.py
common/core/utils.py
common/middleware/__init__.py
common/middleware/logging.py
common/models/__init__.py
common/models/alerts/__init__.py
common/models/alerts/alert.py
common/models/anvil/__init__.py
common/models/anvil/files.py
common/models/hubspot/__init__.py
common/models/hubspot/crm_cards.py
common/models/hubspot/files.py
common/models/hubspot/marketing_events.py
common/models/hubspot/settings.py
common/models/hubspot/webhooks.py
common/models/hubspot/workflow_actions.py
common/models/oauth/__init__.py
common/models/oauth/identity.py
common/models/oauth/tokens.py
common/models/stripe/__init__.py
common/models/stripe/webhooks.py
common/services/__init__.py
common/services/anvil.py
common/services/base.py
common/services/cloud_tasks.py
common/services/constants.py
common/services/email.py
common/services/firestore.py
common/services/google_drive.py
common/services/hubspot.py
common/services/identity.py
common/services/metadata.py
common/services/storage.py
common/services/stripe.py
common/services/text_extract.py
growth_ops_apps_common-1.0.6.dist-info/METADATA
growth_ops_apps_common-1.0.6.dist-info/WHEEL
growth_ops_apps_common-1.0.6.dist-info/top_level.txt
growth_ops_apps_common-1.0.6.dist-info/RECORD
